AUTHORS.rst
CONTRIBUTING.rst
HISTORY.rst
LICENSE
MANIFEST.in
README.rst
setup.cfg
setup.py
django_eighty_days/__init__.py
django_eighty_days/admin.py
django_eighty_days/api.py
django_eighty_days/codegen.py
django_eighty_days/models.py
django_eighty_days/serializers.py
django_eighty_days/urls.py
django_eighty_days.egg-info/PKG-INFO
django_eighty_days.egg-info/SOURCES.txt
django_eighty_days.egg-info/dependency_links.txt
django_eighty_days.egg-info/not-zip-safe
django_eighty_days.egg-info/top_level.txt
django_eighty_days/migrations/0001_initial.py
django_eighty_days/migrations/0002_auto_20150201_2044.py
django_eighty_days/migrations/0003_auto_20150204_1440.py
django_eighty_days/migrations/0004_auto_20150206_0108.py
django_eighty_days/migrations/0005_auto_20150226_1222.py
django_eighty_days/migrations/__init__.py
django_eighty_days/static/css/django_eighty_days.css
django_eighty_days/static/js/django_eighty_days.js
django_eighty_days/templates/django_eighty_days/base.html