Metadata-Version: 1.1
Name: django-eighty-days
Version: 0.3.0
Summary: A django app for around the world in 80 days
Home-page: https://github.com/swfiua/django_eighty_days
Author: Johnny Gill
Author-email: swfiua@gmail.com
License: BSD
Keywords: django_eighty_days
Platform: UNKNOWN
Classifier: Development Status :: 2 - Pre-Alpha
Classifier: Framework :: Django
Classifier: Intended Audience :: Developers
Classifier: License :: OSI Approved :: BSD License
Classifier: Natural Language :: English
Classifier: Programming Language :: Python :: 2
Classifier: Programming Language :: Python :: 2.6
Classifier: Programming Language :: Python :: 2.7
Classifier: Programming Language :: Python :: 3
Classifier: Programming Language :: Python :: 3.3
